[
  {
    "id": "6a23b471-4829-44cf-bf85-7ecd955c7c3a",
    "bio": "Front-end Developer based in Mauritius",
    "job_title": "",
    "location": "",
    "website": "",
    "github": "MrSunshyne",
    "twitter": ""
  },
  {
    "id": "78966047-4716-4afc-856e-46f1430974ed",
    "bio": "",
    "job_title": "",
    "location": "",
    "website": "",
    "github": "saamiyah",
    "twitter": ""
  },
  {
    "id": "5c852db3-4844-4f6d-b6fe-c135963441fb",
    "bio": "",
    "job_title": "",
    "location": "",
    "website": "",
    "github": "kushul",
    "twitter": ""
  },
  {
    "id": "549be7b0-1e7d-4deb-9fb3-273cfe0da5b0",
    "bio": "",
    "job_title": "",
    "location": "",
    "website": "",
    "github": "cedpoilly",
    "twitter": ""
  }
]